moabdx/__init__.py
moabdx/lib.py
moabdx-0.1.0.dist-info/LICENSE
moabdx-0.1.0.dist-info/WHEEL
moabdx-0.1.0.dist-info/METADATA
moabdx-0.1.0.dist-info/RECORD
