Metadata-Version: 2.1
Name: moabdx
Version: 0.1.0
Summary: MoabDX
Author-email: Jackson Coxson <jkcoxson@gmail.com>
Classifier: License :: OSI Approved :: MIT License
Requires-Dist: pandas
Project-URL: Home, https://moabdx.com
